<?xml version="1.0" encoding="utf-8"?>
<resources>
    
    <string name="help_map_ctrl">Χειρισμός χάρτη</string>
    <string name="text_help_map_ctrl">
        <b>1</b> Ελεύθερη λειτουργία\n
        <b>2</b> Ακολούθηση αεροπλάνου\n
        <b>3</b> Κλείδωμα περιστριφής\n
        <b>4</b> Click για επαναφορά\n
    </string>
    
    <string name="help_prediction">Πρόβλεψη</string>
    <string name="text_help_prediction">
        Πρόβλεψη θέσης αεροπλάνου (βασισμένη στην τρέχουσα ταχύτητα και διεύθυνση) σε 10,30 και 90 δεύτερα
    </string>
    
    <string name="faq">FAQ (Συνήθης ερωτήσεις)</string>
    
    <string name="faq_connection">Σύνδεση</string>
    <string name="text_faq_con">
        <b>Πως συνδέομαι?</b>\n
         \u00A0\u00A0 Η εφαρμογή χρειάζεται την διεύθυνση IP του υπολογιστή που τρέχει το War Thunder, για το πως να βρεις την IP σου δες http://ip.junkcode.net \n\n
         
        <b>Έβαλα την IP και ακόμα λέει \"Μη σύνδεση\"</b>\n
         \u00A0\u00A0 Ίσως υπάρχει πρόβλημα με το τοπικό σου δίκτυο κοίταξε http://ip.junkcode.net/help \n\n
         
        <b>Εξακολουθεί να μην συνδέεται!</b>\n
         \u00A0\u00A0 Δεν διάβασες εδώ http://ip.junkcode.net/help, διάβασες?
         \n
    </string>
    
    <string name="faq_extras">Extras</string>
    <string name="text_faq_extra">   
        <b>I donated, where is my code?</b>\n
         \u00A0\u00A0 You should receive code to your email within few minutes after donation, if not contact support@junkcode.net \n\n
         
        <b>I entered code but nothing is unlocked</b>\n
         \u00A0\u00A0 Try restarting the app \n\n
        
    </string>
    <string name="faq_improvement">App improvement</string>
    <string name="text_faq_improve">"  
        <b>I don\'t like something</b>\n
         \u00A0\u00A0 Let us know what - http://junkcode.net/forum/viewforum.php?f=14 \n\n
         
        <b>I found a bug</b>\n
         \u00A0\u00A0 Post it here http://github.com/JunkCode/wtTactMap/issues?state=open \n\n
         
        <b>I have idea for new feature</b>\n
         \u00A0\u00A0 Let us know what - http://junkcode.net/forum/viewforum.php?f=14 \n\n
         
        <b>I want to help with translation/icons/...</b>\n
         \u00A0\u00A0 Some of the resources are already here http://github.com/JunkCode/wtTactMap You can propose modification or add new things. If you have any question or other ideas let us know - http://junkcode.net/forum/viewforum.php?f=14 \n\n
          
    </string>
    
</resources>
